{
    "format": "json",
    "view": "div",
    "doc": "documentation.xml",
    "root": "3.6.9.13",
    "rootNode": "3.6.9.13",
    "id": "v8",
    "odd": "docbook.odd",
    "next": "3.6.9.15",
    "previous": "3.6.9",
    "nextId": "v7",
    "previousId": "versions",
    "switchView": null,
    "content": "<!DOCTYPE html><html><head></head><body><div class=\"content \"><div class=\"tei-section4\" id=\"v8\"><pb-observable data=\"3.6.9.13,3.6.9.13\" emit=\"transcription\">\n        <h3 class=\"tei-title7 title\">What's new in TEI Publisher 8.0.0</h3>\n        <p class=\"tei-para\">Version 8 has been focused on a major rework of the URL handling and redesign of\n          search facilities. A number of further examples gives a better idea of the projects\n          already using TEI Publisher for their editions. There have also been significant changes\n          to connected resources: the tei-publisher-lib, webcomponents library and roaster.</p>\n        <p class=\"tei-para\">See chapter on <pb-link class=\"tei-link3\" uri=\"?odd=docbook.odd&amp;view=div&amp;id=updating\" xml-id=\"updating\" emit=\"transcription\">Updating</pb-link> for information how to update\n          your app to the newest version.</p>\n      </pb-observable></div></div></body></html>",
    "footnotes": "",
    "userParams": {
        "webcomponents": 7
    },
    "collection": "doc"
}