{
    "format": "json",
    "view": "page",
    "doc": "kant_rvernunft_1781.TEI-P5.xml",
    "root": "3.5.4.16.29.11.11.25.25.101.35",
    "rootNode": "3.5.4.16.29.11.11.25.25.101.35",
    "id": null,
    "odd": "dta.odd",
    "next": "3.5.4.16.29.11.11.25.25.105.36",
    "previous": "3.5.4.16.29.11.11.25.25.97.16",
    "nextId": null,
    "previousId": null,
    "switchView": "3.5.4.16",
    "content": "<!DOCTYPE html><html><head></head><body><div class=\"content \"><style type=\"text/css\">.document_aq {\n   font-family:sans-serif\n}\n\n</style><div class=\"tei-div3\"><p class=\"tei-p2\"><pb-facs-link class=\"tei-pb3\" emit=\"transcription\" facs=\"kant_rvernunft_1781/kant_rvernunft_1781_0155_800px.jpg\"></pb-facs-link>\n                                        <span class=\"tei-fw2\">\n                                            <span class=\"tei-hi document_aq\">III.</span> Abſch Vom Verh. d. Verſt.\n                                            zu Gegenſt. ꝛc.</span>\n                                        <br class=\"tei-lb3\"> ren und hoͤchſten (der blos empiriſchen Elemente der\n                                            Er<span class=\"tei-lb1\">-</span><br class=\"tei-lb2\">fahrung) Begriffe, welche die formale\n                                        Einheit der Erfah<span class=\"tei-lb1\">-</span><br class=\"tei-lb2\">rung, und mit ihr alle\n                                        obiective Guͤltigkeit (Wahrheit)<br class=\"tei-lb3\"> der empiriſchen\n                                        Erkentniß moͤglich machen. Dieſe Gruͤnde<br class=\"tei-lb3\"> der\n                                        Recognition des Mannigfaltigen, ſo fern ſie blos die<br class=\"tei-lb3\">\n                                        Form einer Erfahrung uͤberhaupt angehen, ſind nun iene<br class=\"tei-lb3\">\n                                        Categorien. Auf ihnen gruͤndet ſich alſo alle formale<br class=\"tei-lb3\">\n                                        Einheit in der Syntheſis der Einbildungskraft, und ver<span class=\"tei-lb1\">-</span><br class=\"tei-lb2\">mittelſt dieſer auch alles empiriſchen\n                                        Gebrauchs derſelben<br class=\"tei-lb3\"> (in der Recognition, Reproduction,\n                                        Aſſociation, Appre<span class=\"tei-lb1\">-</span><br class=\"tei-lb2\">henſion) bis herunter zu\n                                        den Erſcheinungen, weil dieſe,<br class=\"tei-lb3\"> nur vermittelſt iener\n                                        Elemente der Erkentniß und uͤber<span class=\"tei-lb1\">-</span><br class=\"tei-lb2\">haupt unſerm\n                                        Bewuſtſeyn, mithin uns ſelbſt angehoͤren<br class=\"tei-lb3\"> koͤnnen.</p>\n                                    \n                                    <p class=\"tei-p2\">Die Ordnung und Regelmaͤßigkeit alſo an den Er<span class=\"tei-lb1\">-</span><br class=\"tei-lb2\">ſcheinungen, die wir Natur nennen, bringen wir ſelbſt<br class=\"tei-lb3\">\n                                        hinein, und wuͤrden ſie auch nicht darin finden\n                                        koͤnnen,<br class=\"tei-lb3\"> haͤtten wir ſie nicht, oder die Natur unſeres\n                                        Gemuͤths ur<span class=\"tei-lb1\">-</span><br class=\"tei-lb2\">ſpruͤnglich hineingelegt. Denn\n                                        dieſe Natureinheit ſoll eine<br class=\"tei-lb3\"> nothwendige, d. i. <span class=\"tei-hi document_aq\">a priori</span> gewiſſe Einheit der\n                                            Verknuͤp<span class=\"tei-lb1\">-</span><br class=\"tei-lb2\">fung der Erſcheinungen ſeyn. Wie\n                                        ſollten wir aber wol<br class=\"tei-lb3\">\n                                        <span class=\"tei-hi document_aq\">a priori</span> eine ſynthetiſche Einheit\n                                        auf die Bahn bringen<br class=\"tei-lb3\"> koͤnnen, waͤren nicht in den\n                                        urſpruͤnglichen Erkentnißquel<span class=\"tei-lb1\">-</span><br class=\"tei-lb2\">len unſeres\n                                        Gemuͤths ſubiective Gruͤnde ſolcher Einheit<br class=\"tei-lb3\">\n                                        <span class=\"tei-hi document_aq\">a priori</span> enthalten, und waͤren\n                                        dieſe ſubiective Bedingun<span class=\"tei-lb1\">-</span><br class=\"tei-lb2\">gen nicht zugleich\n                                        obiectiv guͤltig, indem ſie die Gruͤnde<br class=\"tei-lb3\">\n                                        </p><div class=\"tei-fw5 catch\">der</div>\n                                        <br class=\"tei-lb3\">\n                                        <p></p></div></div></body></html>",
    "footnotes": "",
    "userParams": {
        "webcomponents": 7
    },
    "collection": "test"
}